seastartool/__init__.py
seastartool/__main__.py
seastartool/gui.py
seastartool/icon.png
seastartool/main.py
seastartool/jobs/__init__.py
seastartool/jobs/ifcb_to_ecotaxa/__init__.py
seastartool/jobs/ifcb_to_ecotaxa/io.json
seastartool/jobs/ifcb_to_ecotaxa/job.py
seastartool/jobs/ifcb_v4_features/__init__.py
seastartool/jobs/ifcb_v4_features/io.json
seastartool/jobs/ifcb_v4_features/job.py
seastartool-0.6.dist-info/licenses/LICENSE
seastartool-0.6.dist-info/METADATA
seastartool-0.6.dist-info/WHEEL
seastartool-0.6.dist-info/entry_points.txt
seastartool-0.6.dist-info/top_level.txt
seastartool-0.6.dist-info/RECORD
