Metadata-Version: 2.4
Name: seastartool
Version: 0.6
Summary: The Sea-faring System for Tagging, Attribution and Redistribution (SeaSTAR) is a GUI and CLI application for processing biodiversity data collected at sea.
Author-email: Alex Baldwin <contact@alexbaldwin.dev>
License-Expression: GPL-3.0
Project-URL: Homepage, https://github.com/NOC-OI/seastar
Project-URL: Issues, https://github.com/NOC-OI/seastar/issues
Classifier: Programming Language :: Python :: 3
Classifier: Operating System :: OS Independent
Requires-Python: >=3.7
License-File: LICENSE
Requires-Dist: numpy>=1.13.3
Requires-Dist: pyarrow>=12.0.1
Requires-Dist: planktofeatures>=0.1
Requires-Dist: libifcb>=0.8
Requires-Dist: crabdeposit>=0.9
Dynamic: license-file
